agent/__init__.py
agent/agent.py
agent/exceptions.py
agent/handler.py
agent/interrupt.py
agent/job.py
agent_Job_scheduler-0.2.1.dev5.dist-info/LICENSE
agent_Job_scheduler-0.2.1.dev5.dist-info/METADATA
agent_Job_scheduler-0.2.1.dev5.dist-info/NOTICE
agent_Job_scheduler-0.2.1.dev5.dist-info/WHEEL
agent_Job_scheduler-0.2.1.dev5.dist-info/top_level.txt
agent_Job_scheduler-0.2.1.dev5.dist-info/zip-safe
agent_Job_scheduler-0.2.1.dev5.dist-info/RECORD
